{
    "1360917537864552479": {
        "author": "770636197797953566",
        "reason": "No reason provided",
        "status": "open"
    },
    "1360924834552483960": {
        "author": "770636197797953566",
        "reason": "No reason provided",
        "status": "open"
    },
    "1360967583406358559": {
        "author": "770636197797953566",
        "reason": "No reason provided",
        "status": "closed"
    },
    "1360968889424548073": {
        "author": "770636197797953566",
        "reason": "No reason provided",
        "status": "closed"
    }
}